<?xml version="1.0" encoding="UTF-8"?>
<!DOCTYPE builder PUBLIC "-//MMBase/DTD builder config 1.1//EN" "http://www.mmbase.org/dtd/builder_1_1.dtd">
<builder name="valuequestions" maintainer="didactor.nl" version="2" extends="questions">
  <status>active</status>
  <classfile>nl.didactor.education.builders.ValueQuestionBuilder</classfile>
  <searchage>31</searchage>

  <names>
    <!-- singles per language as defined by ISO 639 -->
    <singular xml:lang="nl">Waarde vraag</singular>
    <singular xml:lang="en">Value question</singular>
    <!-- multiple per language as defined by ISO 639 -->
    <plural xml:lang="nl">Waarde vragen</plural>
    <plural xml:lang="en">Value questions</plural>
  </names>

  <descriptions>
    <!-- descriptions per language as defined by ISO 639  -->
    <description xml:lang="nl">
      Een waardevraag geeft de student een aantal opties die hij kan
      kiezen, die alle een andere waarde geven. Ook is het mogelijk om
      open antwoorden op te geven.
    </description>
    <description xml:lang="en">
      A valuequestion gives the student several option that can be chosen,
      which all have a value associated. It is also possible to enter
      open answers.
    </description>
  </descriptions>

  <properties>
    <property name="max-nodes-from-query">99999</property>
  </properties>

  <fieldlist>
    <field>
      <descriptions>
        <!-- descriptions per language as defined by ISO 639  -->
        <description xml:lang="nl">
          Type van de Waarde vraag
          0 = selecteer 1 antwoord
          1 = selecteer meerdere antwoorden
        </description>
        <description xml:lang="en">
          Type of the Value question
          0 = one answers needs to be selected
          1 = multiple answers may be selected
        </description>
      </descriptions>
      <!-- gui related -->
      <gui>
        <guiname xml:lang="nl">Type</guiname>
        <guiname xml:lang="en">Type</guiname>
        <guitype>integer</guitype>
      </gui>
      <!-- editor related  -->
      <editor>
        <positions>
          <!-- position in the input area of the editor -->
          <input>3</input>
          <!-- position in list area of the editor -->
          <list>3</list>
          <!-- position in search area of the editor -->
          <search>3</search>
        </positions>
      </editor>
      <!-- database related  -->
      <db>
        <!-- name of the field in the database -->
        <name>type</name>
        <!-- MMBase datatype and demands on it -->
        <type state="persistent" notnull="true">INTEGER</type>
      </db>
    </field>
    <field>
      <descriptions>
        <!-- descriptions per language as defined by ISO 639  -->
        <description xml:lang="nl">
          Het aantal open antwoorden.
        </description>
        <description xml:lang="en">
          The number of open answers
        </description>
      </descriptions>
      <!-- gui related -->
      <gui>
        <guiname xml:lang="nl">Open Antwoorden</guiname>
        <guiname xml:lang="en">Open Answers</guiname>
        <guitype>integer</guitype>
      </gui>
      <!-- editor related  -->
      <editor>
        <positions>
          <!-- position in the input area of the editor -->
          <input>4</input>
          <!-- position in list area of the editor -->
          <list>4</list>
          <!-- position in search area of the editor -->
          <search>4</search>
        </positions>
      </editor>
      <!-- database related  -->
      <db>
        <!-- name of the field in the database -->
        <name>openanswers</name>
        <!-- MMBase datatype and demands on it -->
        <type state="persistent" notnull="true">INTEGER</type>
      </db>
    </field>
    <field>
      <descriptions>
        <!-- descriptions per language as defined by ISO 639  -->
        <description xml:lang="nl">
          De waarde die aan individuele gegeven open antwoorden wordt toegekend
        </description>
        <description xml:lang="en">
          The value that is being used for indivudual given open answers
        </description>
      </descriptions>
      <!-- gui related -->
      <gui>
        <guiname xml:lang="nl">Waarde voor open antwoorden</guiname>
        <guiname xml:lang="en">Value for open answers</guiname>
        <guitype>integer</guitype>
      </gui>
      <!-- editor related  -->
      <editor>
        <positions>
          <!-- position in the input area of the editor -->
          <input>5</input>
          <!-- position in list area of the editor -->
          <list>5</list>
          <!-- position in search area of the editor -->
          <search>5</search>
        </positions>
      </editor>
      <!-- database related  -->
      <db>
        <!-- name of the field in the database -->
        <name>openanswersvalue</name>
        <!-- MMBase datatype and demands on it -->
        <type state="persistent" notnull="true">INTEGER</type>
      </db>
    </field>
    <field>
      <descriptions>
        <!-- descriptions per language as defined by ISO 639  -->
        <description xml:lang="nl">
          Het minimaal aantal antwoorden dat geselecteerd moet worden
        </description>
        <description xml:lang="en">
          The minimum number of answers that need to be selected
        </description>
      </descriptions>
      <!-- gui related -->
      <gui>
        <guiname xml:lang="nl">Minimum Aantal</guiname>
        <guiname xml:lang="en">Minimal Number</guiname>
        <guitype>integer</guitype>
      </gui>
      <!-- editor related  -->
      <editor>
        <positions>
          <!-- position in the input area of the editor -->
          <input>6</input>
          <!-- position in list area of the editor -->
          <list>6</list>
          <!-- position in search area of the editor -->
          <search>6</search>
        </positions>
      </editor>
      <!-- database related  -->
      <db>
        <!-- name of the field in the database -->
        <name>minanswers</name>
        <!-- MMBase datatype and demands on it -->
        <type state="persistent" notnull="true">INTEGER</type>
      </db>
    </field>
  </fieldlist>
</builder>
