<?xml version="1.0" encoding="utf-8"?>
<posrel exportsource="mmbase://127.0.0.1/media/mm" timestamp="20021123002821">
	<node number="174" owner="default" snumber="122" dnumber="120" rtype="posrel" dir="bidirectional">
		<pos>1</pos>
	</node>

	<node number="172" owner="default" snumber="122" dnumber="118" rtype="posrel" dir="bidirectional">
		<pos>2</pos>
	</node>

	<node number="170" owner="default" snumber="99" dnumber="96" rtype="posrel" dir="bidirectional">
		<pos>1</pos>
	</node>

	<node number="168" owner="default" snumber="94" dnumber="96" rtype="posrel" dir="bidirectional">
		<pos>2</pos>
	</node>

	<node number="166" owner="default" snumber="114" dnumber="110" rtype="posrel" dir="bidirectional">
		<pos>2</pos>
	</node>

	<node number="164" owner="default" snumber="114" dnumber="112" rtype="posrel" dir="bidirectional">
		<pos>1</pos>
	</node>

  <!-- mediaproviders -> urlcomposers -->

	<node number="2004" owner="default" snumber="3001" dnumber="1002" rtype="posrel" dir="bidirectional">
		<pos>1</pos>
	</node>
	<node number="2005" owner="default" snumber="3001" dnumber="1003" rtype="posrel" dir="bidirectional">
		<pos>2</pos>
	</node>
	<node number="2006" owner="default" snumber="3001" dnumber="1000" rtype="posrel" dir="bidirectional">
		<pos>3</pos>
	</node>

	<node number="2008" owner="default" snumber="3002" dnumber="1004" rtype="posrel" dir="bidirectional">
		<pos>1</pos>
	</node>
	<node number="2009" owner="default" snumber="3002" dnumber="1005" rtype="posrel" dir="bidirectional">
		<pos>2</pos>
	</node>
	<node number="2010" owner="default" snumber="3002" dnumber="1000" rtype="posrel" dir="bidirectional">
		<pos>3</pos>
	</node>

  <node number="2011" owner="default" snumber="3003" dnumber="1500" rtype="posrel" dir="bidirectional">
		<pos>1</pos>
	</node>

 
</posrel>
