<?xml version="1.0"?>
<!DOCTYPE wizard-schema PUBLIC "-//MMBase/DTD editwizard 1.0//EN" "http://www.mmbase.org/dtd/wizard-schema_1_0.dtd">
<wizard-schema id="empty">
    <title>Flash Pagina Editor</title>

    <action type="create">
       <object type="flashpages">
           <relation destination="$origin" role="posrel" createdir="source"/>
           <field name="showtitle">1</field>
       </object>
    </action>


    <action type="load">
        <relation destination="mmevents" role="related" />
        <relation destination="attachments" role="related" />
        <relation destination="competencies" role="needcomp" />
        <relation destination="competencies" role="developcomp" />
    </action>

    <action type="delete" />

    <lists>
      <optionlist include="option_lists/layout_ext.xml" />
    </lists>

    <steps>
        <step form-schema="step1" />
        <step form-schema="step2" />
    </steps>

    <form-schema id="step1">
        <title>Flash pagina invoeren</title>
        <field name="name" >
            <prompt>Naam</prompt>
        </field>

      <field name="showtitle" ftype="enum">
         <prompt xml:lang="nl">Titel laten zien</prompt>
         <prompt xml:lang="en">Show title</prompt>
         <optionlist select="boolean" />
      </field>
 

        <field name="text" ftype="html" dtminlength="0">
            <prompt>Tekst</prompt>
        </field>

        <field name="layout" ftype="enum">
            <prompt>Layout</prompt>
            <optionlist select="layout_ext" />
        </field>
 
        <list role="related" extends="config/online/online-list.xml" />
        <list minoccurs="1" maxoccurs="1" role="related" extends="config/attachment/attachments.xml" />
    </form-schema>
    <form-schema id="step2">
        <title>Competenties invoeren</title>
        <field name="name" ftype="data"/>
        <list extends="config/competency/needcompetencies.xml"/>
        <list extends="config/competency/developcompetencies.xml"/>
    </form-schema>
</wizard-schema>
